[
    {
        "Name": "16632",
        "Year": "4",
        "Sgpa": "9.32",
        "Rank": "1",
        "Gender": "",
        "Cgpa": "9.44",
        "Rollno": "16632",
        "Branch": "Architecture",
        "G_rank": "0",
        "Points": "1623"
    },
    {
        "Name": "16610",
        "Year": "4",
        "Sgpa": "8.84",
        "Rank": "2",
        "Gender": "",
        "Cgpa": "8.51",
        "Rollno": "16610",
        "Branch": "Architecture",
        "G_rank": "0",
        "Points": "1464"
    },
    {
        "Name": "16626",
        "Year": "4",
        "Sgpa": "8.84",
        "Rank": "3",
        "Gender": "",
        "Cgpa": "8.09",
        "Rollno": "16626",
        "Branch": "Architecture",
        "G_rank": "0",
        "Points": "1391"
    },
    {
        "Name": "16608",
        "Year": "4",
        "Sgpa": "8.48",
        "Rank": "4",
        "Gender": "",
        "Cgpa": "7.54",
        "Rollno": "16608",
        "Branch": "Architecture",
        "G_rank": "0",
        "Points": "1297"
    },
    {
        "Name": "16622",
        "Year": "4",
        "Sgpa": "8.48",
        "Rank": "5",
        "Gender": "",
        "Cgpa": "7.95",
        "Rollno": "16622",
        "Branch": "Architecture",
        "G_rank": "0",
        "Points": "1368"
    },
    {
        "Name": "16612",
        "Year": "4",
        "Sgpa": "8.32",
        "Rank": "6",
        "Gender": "",
        "Cgpa": "7.53",
        "Rollno": "16612",
        "Branch": "Architecture",
        "G_rank": "0",
        "Points": "1295"
    },
    {
        "Name": "16614",
        "Year": "4",
        "Sgpa": "8.32",
        "Rank": "7",
        "Gender": "",
        "Cgpa": "7.68",
        "Rollno": "16614",
        "Branch": "Architecture",
        "G_rank": "0",
        "Points": "1321"
    },
    {
        "Name": "16602",
        "Year": "4",
        "Sgpa": "8.28",
        "Rank": "8",
        "Gender": "",
        "Cgpa": "7.4",
        "Rollno": "16602",
        "Branch": "Architecture",
        "G_rank": "0",
        "Points": "1272"
    },
    {
        "Name": "16609",
        "Year": "4",
        "Sgpa": "8.28",
        "Rank": "9",
        "Gender": "",
        "Cgpa": "8.48",
        "Rollno": "16609",
        "Branch": "Architecture",
        "G_rank": "0",
        "Points": "1459"
    },
    {
        "Name": "16634",
        "Year": "4",
        "Sgpa": "8.28",
        "Rank": "10",
        "Gender": "",
        "Cgpa": "8.38",
        "Rollno": "16634",
        "Branch": "Architecture",
        "G_rank": "0",
        "Points": "1442"
    },
    {
        "Name": "16616",
        "Year": "4",
        "Sgpa": "8.16",
        "Rank": "11",
        "Gender": "",
        "Cgpa": "7.59",
        "Rollno": "16616",
        "Branch": "Architecture",
        "G_rank": "0",
        "Points": "1306"
    },
    {
        "Name": "16621",
        "Year": "4",
        "Sgpa": "8.08",
        "Rank": "12",
        "Gender": "",
        "Cgpa": "7.54",
        "Rollno": "16621",
        "Branch": "Architecture",
        "G_rank": "0",
        "Points": "1297"
    },
    {
        "Name": "16630",
        "Year": "4",
        "Sgpa": "8",
        "Rank": "13",
        "Gender": "",
        "Cgpa": "6.97",
        "Rollno": "16630",
        "Branch": "Architecture",
        "G_rank": "0",
        "Points": "1198"
    },
    {
        "Name": "16629",
        "Year": "4",
        "Sgpa": "7.88",
        "Rank": "14",
        "Gender": "",
        "Cgpa": "6.65",
        "Rollno": "16629",
        "Branch": "Architecture",
        "G_rank": "0",
        "Points": "1144"
    },
    {
        "Name": "16607",
        "Year": "4",
        "Sgpa": "7.72",
        "Rank": "15",
        "Gender": "",
        "Cgpa": "7.61",
        "Rollno": "16607",
        "Branch": "Architecture",
        "G_rank": "0",
        "Points": "1309"
    },
    {
        "Name": "16613",
        "Year": "4",
        "Sgpa": "7.72",
        "Rank": "16",
        "Gender": "",
        "Cgpa": "6.94",
        "Rollno": "16613",
        "Branch": "Architecture",
        "G_rank": "0",
        "Points": "1194"
    },
    {
        "Name": "16619",
        "Year": "4",
        "Sgpa": "7.72",
        "Rank": "17",
        "Gender": "",
        "Cgpa": "6.97",
        "Rollno": "16619",
        "Branch": "Architecture",
        "G_rank": "0",
        "Points": "1199"
    },
    {
        "Name": "16625",
        "Year": "4",
        "Sgpa": "7.48",
        "Rank": "18",
        "Gender": "",
        "Cgpa": "7.35",
        "Rollno": "16625",
        "Branch": "Architecture",
        "G_rank": "0",
        "Points": "1265"
    },
    {
        "Name": "16628",
        "Year": "4",
        "Sgpa": "7.4",
        "Rank": "19",
        "Gender": "",
        "Cgpa": "6.09",
        "Rollno": "16628",
        "Branch": "Architecture",
        "G_rank": "0",
        "Points": "1047"
    },
    {
        "Name": "16631",
        "Year": "4",
        "Sgpa": "7.36",
        "Rank": "20",
        "Gender": "",
        "Cgpa": "7.35",
        "Rollno": "16631",
        "Branch": "Architecture",
        "G_rank": "0",
        "Points": "1264"
    },
    {
        "Name": "16620",
        "Year": "4",
        "Sgpa": "7.32",
        "Rank": "21",
        "Gender": "",
        "Cgpa": "6.61",
        "Rollno": "16620",
        "Branch": "Architecture",
        "G_rank": "0",
        "Points": "1137"
    },
    {
        "Name": "16603",
        "Year": "4",
        "Sgpa": "7.16",
        "Rank": "22",
        "Gender": "",
        "Cgpa": "7.19",
        "Rollno": "16603",
        "Branch": "Architecture",
        "G_rank": "0",
        "Points": "1237"
    },
    {
        "Name": "16606",
        "Year": "4",
        "Sgpa": "6.96",
        "Rank": "23",
        "Gender": "",
        "Cgpa": "6.7",
        "Rollno": "16606",
        "Branch": "Architecture",
        "G_rank": "0",
        "Points": "1153"
    },
    {
        "Name": "16624",
        "Year": "4",
        "Sgpa": "6.8",
        "Rank": "24",
        "Gender": "",
        "Cgpa": "6.73",
        "Rollno": "16624",
        "Branch": "Architecture",
        "G_rank": "0",
        "Points": "1158"
    },
    {
        "Name": "16601",
        "Year": "4",
        "Sgpa": "6.24",
        "Rank": "25",
        "Gender": "",
        "Cgpa": "6.3",
        "Rollno": "16601",
        "Branch": "Architecture",
        "G_rank": "0",
        "Points": "1084"
    },
    {
        "Name": "16611",
        "Year": "4",
        "Sgpa": "6.04",
        "Rank": "26",
        "Gender": "",
        "Cgpa": "5.21",
        "Rollno": "16611",
        "Branch": "Architecture",
        "G_rank": "0",
        "Points": "896"
    },
    {
        "Name": "16627",
        "Year": "4",
        "Sgpa": "6.04",
        "Rank": "27",
        "Gender": "",
        "Cgpa": "4.49",
        "Rollno": "16627",
        "Branch": "Architecture",
        "G_rank": "0",
        "Points": "772"
    },
    {
        "Name": "16623",
        "Year": "4",
        "Sgpa": "5.6",
        "Rank": "28",
        "Gender": "",
        "Cgpa": "6.37",
        "Rollno": "16623",
        "Branch": "Architecture",
        "G_rank": "0",
        "Points": "1096"
    },
    {
        "Name": "16615",
        "Year": "4",
        "Sgpa": "5.44",
        "Rank": "29",
        "Gender": "",
        "Cgpa": "6.34",
        "Rollno": "16615",
        "Branch": "Architecture",
        "G_rank": "0",
        "Points": "1090"
    },
    {
        "Name": "16618",
        "Year": "4",
        "Sgpa": "4.56",
        "Rank": "30",
        "Gender": "",
        "Cgpa": "4.41",
        "Rollno": "16618",
        "Branch": "Architecture",
        "G_rank": "0",
        "Points": "758"
    },
    {
        "Name": "16633",
        "Year": "4",
        "Sgpa": "3.64",
        "Rank": "31",
        "Gender": "",
        "Cgpa": "4.88",
        "Rollno": "16633",
        "Branch": "Architecture",
        "G_rank": "0",
        "Points": "840"
    },
    {
        "Name": "16604",
        "Year": "4",
        "Sgpa": "1.54",
        "Rank": "32",
        "Gender": "",
        "Cgpa": "3.06",
        "Rollno": "16604",
        "Branch": "Architecture",
        "G_rank": "0",
        "Points": "370"
    },
    {
        "Name": "16617",
        "Year": "4",
        "Sgpa": "1.36",
        "Rank": "33",
        "Gender": "",
        "Cgpa": "4.44",
        "Rollno": "16617",
        "Branch": "Architecture",
        "G_rank": "0",
        "Points": "763"
    },
    {
        "Name": "16605",
        "Year": "4",
        "Sgpa": "0",
        "Rank": "34",
        "Gender": "",
        "Cgpa": "0",
        "Rollno": "16605",
        "Branch": "Architecture",
        "G_rank": "0",
        "Points": "0"
    }
]